convenient_ai/__init__.py
convenient_ai/nlp/__api__/__init__.py
convenient_ai/nlp/__common__/Sentence.py
convenient_ai/nlp/__common__/Text.py
convenient_ai/nlp/__common__/Token.py
convenient_ai/nlp/__common__/__init__.py
convenient_ai/nlp/__common__/io/Json.py
convenient_ai/nlp/__common__/io/__init__.py
convenient_ai/nlp/__init__.py
convenient_ai/nlp/spacy/ConvenientSpacy.py
convenient_ai/nlp/spacy/__init__.py
convenient_ai/nlp/spacy/custom/RegExMatcher.py
convenient_ai/nlp/spacy/custom/__init__.py
convenient_ai/nlp/spacy/types/RulePattern.py
convenient_ai/nlp/spacy/types/__init__.py
convenient_ai-0.2.0.dist-info/entry_points.txt
convenient_ai-0.2.0.dist-info/LICENSE
convenient_ai-0.2.0.dist-info/WHEEL
convenient_ai-0.2.0.dist-info/METADATA
convenient_ai-0.2.0.dist-info/RECORD
